ka_flaskrun/__init__.py
ka_flaskrun/core.py
ka_flaskrun-1.3.3.dist-info/licenses/LICENSE
ka_flaskrun-1.3.3.dist-info/METADATA
ka_flaskrun-1.3.3.dist-info/WHEEL
ka_flaskrun-1.3.3.dist-info/top_level.txt
ka_flaskrun-1.3.3.dist-info/RECORD
