Metadata-Version: 2.4
Name: ka_flaskrun
Version: 1.3.3
Summary: License verification middleware for Flask apps
Home-page: https://github.com/saadelkafi
Author: Saad EL KAFI
Author-email: mrsaadkafi@gmail.com
Classifier: Programming Language :: Python :: 3
Classifier: Framework :: Flask
Classifier: License :: OSI Approved :: MIT License
Classifier: Operating System :: OS Independent
Requires-Python: >=3.9
License-File: LICENSE
Requires-Dist: flask
Requires-Dist: requests
Dynamic: author
Dynamic: author-email
Dynamic: classifier
Dynamic: description
Dynamic: description-content-type
Dynamic: home-page
Dynamic: license-file
Dynamic: requires-dist
Dynamic: requires-python
Dynamic: summary
